LexiDecay/__init__.py
LexiDecay/core.py
lexidecay-1.0.0.dist-info/licenses/LICENSE
lexidecay-1.0.0.dist-info/METADATA
lexidecay-1.0.0.dist-info/WHEEL
lexidecay-1.0.0.dist-info/top_level.txt
lexidecay-1.0.0.dist-info/RECORD
