Metadata-Version: 2.4
Name: LexiDecay
Version: 1.0.0
Summary: LexiDecay is a semi-supervised lexical weighting model for unstructured text. It classifies content by adaptive word-frequency decay and soft lexical scoring. Fast (O(n·m)), language-flexible, and training-free — ideal for topic classification, semantic filtering, and intent detection. 
Author: Mohammad Taha Gorji
Author-email: MohammadTahaGorjiProfile@gmail.com
Classifier: Programming Language :: Python :: 3
Classifier: Operating System :: OS Independent
Requires-Python: >=3.1
License-File: LICENSE
Dynamic: author
Dynamic: author-email
Dynamic: classifier
Dynamic: description
Dynamic: description-content-type
Dynamic: license-file
Dynamic: requires-python
Dynamic: summary
